LICENSE.md
MANIFEST.in
requirements.txt
setup.py
cb_bus_client/__init__.py
cb_bus_client/__main__.py
cb_bus_client/client.py
cb_bus_client/conf.py
cb_bus_client/encryption.py
cb_bus_client/message.py
cb_bus_client/scheduler.py
cb_bus_client/send_func.py
cb_bus_client/util.py
cb_bus_client.egg-info/PKG-INFO
cb_bus_client.egg-info/SOURCES.txt
cb_bus_client.egg-info/dependency_links.txt
cb_bus_client.egg-info/requires.txt
cb_bus_client.egg-info/top_level.txt