Metadata-Version: 2.1
Name: cb-bus-client
Version: 0.0.10
Summary: Chatterbox Messagebus Client
Home-page: https://github.com/HelloChatterbox/chatterbox-bus-client
Author: Kevin Elgan
Author-email: kevin@hellochatterbox.com
License: Apache-2.0
Platform: UNKNOWN
Classifier: Development Status :: 4 - Beta
Classifier: Intended Audience :: Developers
Classifier: License :: OSI Approved :: Apache Software License
Classifier: Programming Language :: Python :: 3.5
Classifier: Programming Language :: Python :: 3.6
Classifier: Programming Language :: Python :: 3.7
Classifier: Programming Language :: Python :: 3.8
